vica/__init__.py
vica/classify.py
vica/get_features.py
vica/khmer_features.py
vica/minhash.py
vica/prodigal.py
vica/split_shred.py
vica/tfrecord_maker.py
vica/train_eval.py
vica/vica_cli.py
vica/data/config_default.yml
vica/data/organelles.json
vica/data/phylum.txt
vica-0.1.5.data/scripts/vica_cli.py
vica-0.1.5.dist-info/DESCRIPTION.rst
vica-0.1.5.dist-info/METADATA
vica-0.1.5.dist-info/RECORD
vica-0.1.5.dist-info/WHEEL
vica-0.1.5.dist-info/metadata.json
vica-0.1.5.dist-info/top_level.txt
