Metadata-Version: 2.0
Name: vica
Version: 0.1.5
Summary: find highly divergent DNA and RNA viruses in microbiomes
Home-page: http://github.com/usda-ars-gbru/vica
Author: Adam R. Rivers, Qingpeng Zhang
Author-email: adam.rivers@ars.usda.gov
License: License :: OSI Approved :: BSD License
Keywords: virus classifier metagenome RNA DNA microbiome tensorflow
Platform: UNKNOWN
Classifier: Topic :: Scientific/Engineering :: Bio-Informatics
Classifier: Topic :: Scientific/Engineering :: Artificial Intelligence
Classifier: Programming Language :: Python :: 3.6
Classifier: Programming Language :: Python :: 3.5
Classifier: Development Status :: 3 - Alpha
Requires-Python: >3.5
Requires-Dist: tensorflow (>=1.4)
Requires-Dist: pandas (>=0.20.3)
Requires-Dist: numpy (>=1.14)
Requires-Dist: biopython (>=1.70)
Requires-Dist: scipy (>=0.19.0)
Requires-Dist: khmer (>=2.1.1)
Requires-Dist: ete3
Requires-Dist: pyfaidx (>=0.5)
Requires-Dist: pyyaml
Requires-Dist: scikit-learn (>=0.19.0)
